opencal/__init__.py
opencal/config.py
opencal/models.py
opencal/py.typed
opencal/statistics.py
opencal/core/__init__.py
opencal/core/mocks.py
opencal/core/tags.py
opencal/core/professor/__init__.py
opencal/core/professor/professor.py
opencal/core/professor/acquisition/__init__.py
opencal/core/professor/acquisition/arthur.py
opencal/core/professor/acquisition/baptiste.py
opencal/core/professor/acquisition/charles.py
opencal/core/professor/acquisition/denis.py
opencal/core/professor/acquisition/ernest.py
opencal/core/professor/acquisition/professor.py
opencal/core/professor/acquisition/ralph.py
opencal/core/professor/acquisition/randy.py
opencal/core/professor/consolidation/__init__.py
opencal/core/professor/consolidation/alice.py
opencal/core/professor/consolidation/berenice.py
opencal/core/professor/consolidation/brutus.py
opencal/core/professor/consolidation/celia.py
opencal/core/professor/consolidation/doreen.py
opencal/core/professor/consolidation/professor.py
opencal/io/__init__.py
opencal/io/database.py
opencal-4.0.2.dist-info/licenses/AUTHORS
opencal-4.0.2.dist-info/licenses/LICENSE
opencal-4.0.2.dist-info/METADATA
opencal-4.0.2.dist-info/WHEEL
opencal-4.0.2.dist-info/entry_points.txt
opencal-4.0.2.dist-info/top_level.txt
opencal-4.0.2.dist-info/RECORD
