Metadata-Version: 2.4
Name: opencal
Version: 4.0.2
Summary: OpenCAL core library for Python
Author-email: Jérémie DECOCK <jd.jdhp@gmail.com>
Classifier: Development Status :: 4 - Beta
Classifier: Intended Audience :: Developers
Classifier: Natural Language :: English
Classifier: Operating System :: OS Independent
Classifier: Programming Language :: Python :: 3
Classifier: Topic :: Software Development :: Libraries
Requires-Python: >=3.11
License-File: LICENSE
License-File: AUTHORS
Requires-Dist: pandas
Requires-Dist: pydantic~=2.9.2
Requires-Dist: pydantic_core~=2.23.4
Requires-Dist: pyyaml
Requires-Dist: sqlmodel~=0.0.21
Dynamic: license-file
